tests/__init__.py
tests/models.py
tests/testMongo.py
tests/tests.py
yModel/__init__.py
yModel/mongo.py
yModel/utils.py
yModel-0.0.2.dist-info/LICENSE
yModel-0.0.2.dist-info/METADATA
yModel-0.0.2.dist-info/WHEEL
yModel-0.0.2.dist-info/top_level.txt
yModel-0.0.2.dist-info/RECORD
