Metadata-Version: 2.1
Name: yModel
Version: 0.0.2
Summary: Marshmallow subclasses with extended features
Home-page: https://github.com/Garito/yModel
Author: Garito
Author-email: garito@gmail.com
License: MIT
Keywords: data schema marshmallow trees materialized_paths mongodb
Platform: UNKNOWN
Classifier: Development Status :: 4 - Beta
Classifier: Environment :: Plugins
Classifier: Intended Audience :: Developers
Classifier: License :: OSI Approved :: MIT License
Classifier: Programming Language :: Python :: 3
Classifier: Topic :: Database
Requires-Python: >=3.6
Requires-Dist: marshmallow
Requires-Dist: motor
Requires-Dist: python-slugify
